logcontext/__init__.py
logcontext/_main.py
logcontext-0.1.1.dist-info/METADATA
logcontext-0.1.1.dist-info/WHEEL
logcontext-0.1.1.dist-info/top_level.txt
logcontext-0.1.1.dist-info/RECORD
