Metadata-Version: 2.1
Name: logcontext
Version: 0.1.1
Summary: A simple logging system for (async) contexts
Author-email: Matthias Urlichs <matthias@urlichs.de>
Project-URL: homepage, https://m-o-a-t.org
Project-URL: repository, https://github.com/M-o-a-T/logcontext
Keywords: async,logging,context
Classifier: Intended Audience :: Developers
Classifier: Programming Language :: Python :: 3
Classifier: Framework :: AsyncIO
Classifier: Framework :: Trio
Classifier: Framework :: AnyIO
Classifier: License :: OSI Approved
Classifier: Development Status :: 4 - Beta
Requires-Python: >=3.7
